{
  "regionInfo": {
    "PayCallbackUrl": "http://127.0.0.1/pay-callback",
    "AreaType": "CN",
    "CdkeyUrl": "http://127.0.0.1",
    "PrivacyPolicyUrl": "",
    "FeedbackUrl": "",
    "BulletinUrl": "",
    "SecretKey": "",
    "ResourceUrl": "https://autopatchcn.yuanshen.com/client_game_res/5.0_live",
    "DataUrl": "https://autopatchcn.yuanshen.com/client_design_data/5.0_live",
    "ResourceUrlBak": "5.0_live",
    "DataUrlBak": "",
    "ClientDataVersion": 26547926,
    "ClientSilenceDataVersion": 26530839,
    "ClientDataMd5": "",
    "ClientSilenceDataMd5": "",
    "ClientVersionSuffix": "3d43078d67",
    "ClientSilenceVersionSuffix": "185bf02ea7",
    "ResVersionConfig": {
      "Relogin": false,
      "Md5": "{\"remoteName\": \"res_versions_external\", \"md5\": \"5f99cdd2660028d32e2d16e696cb7949\", \"hash\": \"a5f3031b9e400e8b\", \"fileSize\": 218240}\r\n{\"remoteName\": \"res_versions_medium\", \"md5\": \"aa1afe72dd4897b44f40c515edf9a51f\", \"hash\": \"6895c251c464860d\", \"fileSize\": 139992}\r\n{\"remoteName\": \"res_versions_streaming\", \"md5\": \"e07b66cef8e41bb12157d87d197a08c1\", \"hash\": \"c3885fbc2eb9b469\", \"fileSize\": 128380}\r\n{\"remoteName\": \"base_revision\", \"md5\": \"149cad27b543e345df504a496949ec7d\", \"hash\": \"8bb70126e5cd8ba0\", \"fileSize\": 19}\r\n{\"remoteName\": \"patch_node_versions\", \"md5\": \"7b2578939883dbcb706d96b5c896f661\", \"hash\": \"d6f8dd374674c20b\", \"fileSize\": 1276}",
      "Version": 26458901,
      "ReleaseTotalSize": "0",
      "VersionSuffix": "befdda25ff",
      "Branch": "5.0_live"
    }
  },
  "StopServer": {
    "StopBeginTime": 1577808000,
    "StopEndTime": 1893427200,
    "Url": "https://vme50.icu/",
    "ContentMsg": "芜湖起飞"
  }
}