{
  "regionInfo": {
    "PayCallbackUrl": "http://127.0.0.1/pay-callback",
    "AreaType": "JP",
    "CdkeyUrl": "http://127.0.0.1",
    "PrivacyPolicyUrl": "",
    "FeedbackUrl": "",
    "BulletinUrl": "",
    "SecretKey": "",
    "ResourceUrl": "https://autopatchhk.yuanshen.com/client_game_res/5.0_live",
    "DataUrl": "https://autopatchhk.yuanshen.com/client_design_data/5.0_live",
    "ResourceUrlBak": "5.0_live",
    "DataUrlBak": "",
    "ClientDataVersion": 26720294,
    "ClientSilenceDataVersion": 26720294,
    "ClientDataMd5": "{\"remoteName\": \"data_versions\", \"md5\": \"48d41900b91fa0f8dd3424b5b576cb93\", \"hash\": \"fc115986023a4616\", \"fileSize\": 68545}\r\n{\"remoteName\": \"data_versions_medium\", \"md5\": \"61efdc32fcc732dc1c41ed24dc96d628\", \"hash\": \"8d422e3a8501667c\", \"fileSize\": 6662}",
    "ClientSilenceDataMd5": "{\"remoteName\": \"data_versions\", \"md5\": \"507cab5756da600a5915b81c976dc534\", \"hash\": \"132bcda5c256e605\", \"fileSize\": 522}",
    "ClientVersionSuffix": "79e8f3e212",
    "ClientSilenceVersionSuffix": "79e8f3e212",
    "ResVersionConfig": {
      "Relogin": false,
      "Md5": "{\"remoteName\": \"res_versions_external\", \"md5\": \"114f536781fa3aa4149818776d247e53\", \"hash\": \"c59bc69762e5a5d0\", \"fileSize\": 48648}\r\n{\"remoteName\": \"res_versions_medium\", \"md5\": \"154126efada1d14580264e2851c4c294\", \"hash\": \"5af710d6d77c28c1\", \"fileSize\": 35717}\r\n{\"remoteName\": \"res_versions_streaming\", \"md5\": \"6005c46f5c3fbb2235db54160fb84f86\", \"hash\": \"f36cf5ae60b52d85\", \"fileSize\": 34620}\r\n{\"remoteName\": \"base_revision\", \"md5\": \"149cad27b543e345df504a496949ec7d\", \"hash\": \"8bb70126e5cd8ba0\", \"fileSize\": 19}\r\n{\"remoteName\": \"patch_node_versions\", \"md5\": \"a37a6c3fa048857a8eb79aa80ec7c84b\", \"hash\": \"4c7499e323ea3c04\", \"fileSize\": 845}",
      "Version": 26709834,
      "ReleaseTotalSize": "0",
      "VersionSuffix": "034791c61b",
      "Branch": "5.0_live"
    }
  },
  "StopServer": {
    "StopBeginTime": 1577808000,
    "StopEndTime": 1893427200,
    "Url": "https://vme50.icu/",
    "ContentMsg": "芜湖起飞"
  }
}